gitguard/__init__.py
gitguard/cli.py
gitguard/config.py
gitguard/exceptions.py
gitguard/validator.py
gitguard-1.0.2.dist-info/licenses/LICENSE
gitguard-1.0.2.dist-info/METADATA
gitguard-1.0.2.dist-info/WHEEL
gitguard-1.0.2.dist-info/entry_points.txt
gitguard-1.0.2.dist-info/top_level.txt
gitguard-1.0.2.dist-info/RECORD
