Metadata-Version: 2.4
Name: gitguard
Version: 1.0.2
Summary: Enterprise-grade secure git workflow system - Part of Project Himalaya demonstrating AI-human collaboration
Home-page: https://github.com/herbbowers/gitguard
Author: Herbert J. Bowers (Project Creator), Claude (Anthropic) - Technical Implementation
Author-email: HimalayaProject1@gmail.com
Project-URL: Bug Reports, https://github.com/herbbowers/gitguard/issues
Project-URL: Source, https://github.com/herbbowers/gitguard
Project-URL: Documentation, https://gitguard.dev
Project-URL: Changelog, https://github.com/herbbowers/gitguard/blob/main/CHANGELOG.md
Keywords: git,security,credentials,secrets,devops,devsecops,audit,compliance,workflow,automation,enterprise
Classifier: Development Status :: 5 - Production/Stable
Classifier: Intended Audience :: Developers
Classifier: Intended Audience :: System Administrators
Classifier: Intended Audience :: Information Technology
Classifier: Topic :: Security
Classifier: Topic :: Software Development :: Version Control :: Git
Classifier: Topic :: Software Development :: Quality Assurance
Classifier: License :: OSI Approved :: MIT License
Classifier: Programming Language :: Python :: 3
Classifier: Programming Language :: Python :: 3.8
Classifier: Programming Language :: Python :: 3.9
Classifier: Programming Language :: Python :: 3.10
Classifier: Programming Language :: Python :: 3.11
Classifier: Programming Language :: Python :: 3.12
Classifier: Operating System :: OS Independent
Classifier: Environment :: Console
Requires-Python: >=3.8
License-File: LICENSE
Requires-Dist: GitPython>=3.1.30
Requires-Dist: regex>=2022.10.31
Requires-Dist: PyYAML>=6.0
Requires-Dist: click>=8.0.0
Requires-Dist: python-dateutil>=2.8.0
Requires-Dist: pathlib2>=2.3.7; python_version < "3.4"
Requires-Dist: subprocess32>=3.5.4; python_version < "3.3"
Provides-Extra: dev
Requires-Dist: pytest>=7.0.0; extra == "dev"
Requires-Dist: pytest-cov>=4.0.0; extra == "dev"
Requires-Dist: black>=22.0.0; extra == "dev"
Requires-Dist: flake8>=4.0.0; extra == "dev"
Requires-Dist: mypy>=0.991; extra == "dev"
Requires-Dist: pre-commit>=2.20.0; extra == "dev"
Provides-Extra: enterprise
Requires-Dist: requests>=2.28.0; extra == "enterprise"
Requires-Dist: pyyaml>=6.0; extra == "enterprise"
Requires-Dist: click>=8.0.0; extra == "enterprise"
Requires-Dist: jinja2>=3.0.0; extra == "enterprise"
Dynamic: author
Dynamic: author-email
Dynamic: classifier
Dynamic: description
Dynamic: description-content-type
Dynamic: home-page
Dynamic: keywords
Dynamic: license-file
Dynamic: project-url
Dynamic: provides-extra
Dynamic: requires-dist
Dynamic: requires-python
Dynamic: summary
